AUTHORS.rst
CONTRIBUTING.rst
HISTORY.rst
LICENSE
MANIFEST.in
README.rst
setup.cfg
setup.py
docs/Makefile
docs/authors.rst
docs/conf.py
docs/contributing.rst
docs/history.rst
docs/index.rst
docs/installation.rst
docs/make.bat
docs/readme.rst
docs/usage.rst
ozone/__init__.py
ozone/ozone.py
ozone.egg-info/PKG-INFO
ozone.egg-info/SOURCES.txt
ozone.egg-info/dependency_links.txt
ozone.egg-info/not-zip-safe
ozone.egg-info/requires.txt
ozone.egg-info/top_level.txt
ozone/filters/__init__.py
ozone/filters/arns.py
ozone/filters/regexes.py
ozone/handlers/__init__.py
ozone/handlers/lambda_tools.py
ozone/handlers/stack_manage.py
ozone/handlers/template_manage.py
ozone/outputs/__init__.py
ozone/resolvers/__init__.py
ozone/resolvers/codebuild/__init__.py
ozone/resolvers/codebuild/runtime.py
ozone/resolvers/iam/__init__.py
ozone/resolvers/kms/__init__.py
ozone/resolvers/organizations/__init__.py
ozone/resolvers/s3/__init__.py
ozone/resources/__init__.py
ozone/resources/devtools/__init__.py
ozone/resources/devtools/buildproject.py
ozone/resources/devtools/pipeline.py
ozone/resources/iam/__init__.py
ozone/resources/iam/policies/__init__.py
ozone/resources/iam/policies/s3_replica_kms.py
ozone/resources/iam/roles/__init__.py
ozone/resources/iam/roles/pipeline_role.py
ozone/resources/kms/__init__.py
ozone/resources/kms/alias.py
ozone/resources/kms/key.py
ozone/resources/kms/policy.py
ozone/resources/organizations/__init__.py
ozone/resources/s3/__init__.py
ozone/resources/s3/bucket.py
ozone/resources/s3/cloudtrail_policy.py
ozone/tags/__init__.py
ozone/templates/__init__.py
ozone/templates/awslambda.py
ozone/templates/awslambdalayer.py
ozone/templates/awslambdalayer_pipeline.py
tests/test_ozone.py