Metadata-Version: 1.1
Name: ozone
Version: 0.1.0
Summary: Python Library wrapping Troposphere and boto3 to manage AWS via CFN
Home-page: https://github.com/johnpreston/ozone
Author: John Mille
Author-email: john@lambda-my-aws.io
License: Apache Software License 2.0
Keywords: ozone
Platform: UNKNOWN
Classifier: Development Status :: 2 - Pre-Alpha
Classifier: Intended Audience :: Developers
Classifier: License :: OSI Approved :: Apache Software License
Classifier: Natural Language :: English
Classifier: Programming Language :: Python :: 3.7
